lbjobmonitor/__init__.py
lbjobmonitor/__version__.py
lbjobmonitor/message.py
lbjobmonitor/models.py
lbjobmonitor/monitor.py
lbjobmonitor/storage.py
lbjobmonitor-0.9.2.dist-info/LICENSE
lbjobmonitor-0.9.2.dist-info/METADATA
lbjobmonitor-0.9.2.dist-info/WHEEL
lbjobmonitor-0.9.2.dist-info/top_level.txt
lbjobmonitor-0.9.2.dist-info/RECORD
