Metadata-Version: 2.1
Name: lbjobmonitor
Version: 0.9.2
Summary: Job Monitor.
Home-page: https://github.com/vicalloy/jobmonitor/
Author: vicalloy
Author-email: zbirder@gmail.com
License: Apache 2.0
Platform: UNKNOWN
Classifier: Development Status :: 3 - Alpha
Classifier: Intended Audience :: End Users/Desktop
Classifier: Natural Language :: English
Classifier: License :: OSI Approved :: Apache Software License
Classifier: Programming Language :: Python
Classifier: Programming Language :: Python :: 3.5
Classifier: Programming Language :: Python :: 3.6
Classifier: Programming Language :: Python :: 3.7
Classifier: Programming Language :: Python :: Implementation :: CPython
Classifier: Programming Language :: Python :: Implementation :: PyPy
Requires-Python: >=3.5
License-File: LICENSE
Requires-Dist: requests
Requires-Dist: beautifulsoup4
Provides-Extra: slack
Requires-Dist: slackclient ; extra == 'slack'
Provides-Extra: telegram
Requires-Dist: python-telegram-bot ; extra == 'telegram'
